LICENSE.txt
README.md
setup.py
detexe/__init__.py
detexe/cli.py
detexe/log.py
detexe/settings.py
detexe.egg-info/PKG-INFO
detexe.egg-info/SOURCES.txt
detexe.egg-info/dependency_links.txt
detexe.egg-info/entry_points.txt
detexe.egg-info/requires.txt
detexe.egg-info/top_level.txt
detexe/pea/__init__.py
detexe/pea/attacker.py
detexe/pea/blackbox/__init__.py
detexe/pea/blackbox/c_black_box_format_exploit_evasion.py
detexe/pea/blackbox/c_black_box_padding_evasion.py
detexe/pea/blackbox/c_blackbox_header_problem.py
detexe/pea/blackbox/c_blackbox_problem.py
detexe/pea/blackbox/c_gamma_evasion.py
detexe/pea/blackbox/c_gamma_sections_evasion.py
detexe/pea/blackbox/c_gamma_shift_problem.py
detexe/pea/blackbox/c_gammapi_evasion.py
detexe/pea/blackbox/ga/__init__.py
detexe/pea/blackbox/ga/c_base_genetic_engine.py
detexe/pea/model/__init__.py
detexe/pea/model/c_classifier_ped.py
detexe/pea/model/c_feature_extractor_wrapper_phi.py
detexe/pea/model/c_wrapper_phi.py
detexe/pea/utils/__init__.py
detexe/pea/utils/exceptions.py
detexe/pea/utils/extend_pe.py
detexe/ped/__init__.py
detexe/ped/classifier.py
detexe/ped/detector.py
detexe/ped/extractor.py
detexe/ped/file_vectorizer.py
detexe/ped/metrics.py
detexe/ped/features/__init__.py
detexe/ped/features/base_feature.py
detexe/ped/features/byte_entropy_histogram.py
detexe/ped/features/byte_histogram.py
detexe/ped/features/data_directories.py
detexe/ped/features/exports_info.py
detexe/ped/features/general_file_info.py
detexe/ped/features/header_file_info.py
detexe/ped/features/imports_info.py
detexe/ped/features/opcode_vectors.py
detexe/ped/features/section_info.py
detexe/ped/features/string_extractor.py
detexe/ped/features/feature_helpers/__init__.py
detexe/ped/features/feature_helpers/train_opcodes_vectors.py