Metadata-Version: 2.1
Name: detexe
Version: 0.0.2.3
Summary: A framework to create malware detectors based on machine learning.
Home-page: https://github.com/fededames/detexe
Author: Federico Damian
Author-email: fededames@gmail.com
License: GPL 3.0
Keywords: malware, pe, machine learning, static analysis, adversarial attack
Platform: UNKNOWN
Classifier: Development Status :: 5 - Production/Stable
Classifier: Intended Audience :: Developers
Classifier: Intended Audience :: Education
Classifier: Intended Audience :: Science/Research
Classifier: Topic :: Scientific/Engineering
Classifier: Topic :: Scientific/Engineering :: Artificial Intelligence
Classifier: Topic :: Security
Classifier: Topic :: Security :: Cryptography
Classifier: Topic :: Software Development
Classifier: Topic :: Software Development :: Libraries
Classifier: Topic :: Software Development :: Libraries :: Python Modules
Classifier: Programming Language :: Python :: 3
Provides-Extra: dev
License-File: LICENSE.txt
